aiolancium/__about__.py
aiolancium/__init__.py
aiolancium/auth.py
aiolancium/client.py
aiolancium/decorator.py
aiolancium/interfaces/__init__.py
aiolancium/interfaces/_decorator.py
aiolancium/interfaces/_proxy.py
aiolancium/proxy.py
aiolancium/resources/__init__.py
aiolancium/resources/api.json
aiolancium/resources/openapi.py
aiolancium/utilities/__init__.py
aiolancium/utilities/utilities.py
aiolancium-0.2.2.dist-info/LICENSE
aiolancium-0.2.2.dist-info/WHEEL
aiolancium-0.2.2.dist-info/METADATA
aiolancium-0.2.2.dist-info/RECORD
