Metadata-Version: 2.1
Name: aiolancium
Version: 0.2.2
Summary: AsyncIO Client for Lancium
License: MIT
Keywords: asyncio,lancium,compute client
Author: Manuel Giffels
Author-email: giffels@gmail.com
Requires-Python: >=3.6.2,<4.0.0
Classifier: Development Status :: 3 - Alpha
Classifier: Framework :: AsyncIO
Classifier: Intended Audience :: Developers
Classifier: Intended Audience :: Information Technology
Classifier: Intended Audience :: Science/Research
Classifier: Intended Audience :: System Administrators
Classifier: License :: OSI Approved :: MIT License
Classifier: Operating System :: OS Independent
Classifier: Programming Language :: Python :: 3
Classifier: Programming Language :: Python :: 3.7
Classifier: Programming Language :: Python :: 3.8
Classifier: Programming Language :: Python :: 3.9
Classifier: Programming Language :: Python :: 3.10
Classifier: Programming Language :: Python :: 3.11
Classifier: Programming Language :: Python :: 3.10
Classifier: Programming Language :: Python :: 3.6
Classifier: Programming Language :: Python :: 3.7
Classifier: Programming Language :: Python :: 3.8
Classifier: Programming Language :: Python :: 3.9
Classifier: Topic :: Internet :: WWW/HTTP :: Session
Classifier: Topic :: Utilities
Provides-Extra: doc
Provides-Extra: test
Requires-Dist: aioresponses (>=0.7.3,<0.8.0); extra == "test"
Requires-Dist: black (<=22.8.0); extra == "test"
Requires-Dist: flake8 (>=5.0.4,<6.0.0); extra == "test"
Requires-Dist: flake8-bugbear (==22.9.23); extra == "test"
Requires-Dist: jsonref (>=1.0.0,<2.0.0)
Requires-Dist: pyjwt (<=2.4.0)
Requires-Dist: simple-rest-client (==0.5.4)
Requires-Dist: sphinx (==4.3.1); extra == "doc"
Requires-Dist: sphinx-rtd-theme (>=1.1.1,<2.0.0); extra == "doc"
Requires-Dist: sphinxcontrib-contentui (>=0.2.5,<0.3.0); extra == "doc"
